README.md
setup.py
django_toolware.egg-info/PKG-INFO
django_toolware.egg-info/SOURCES.txt
django_toolware.egg-info/dependency_links.txt
django_toolware.egg-info/requires.txt
django_toolware.egg-info/top_level.txt
toolware/__init__.py
toolware/apps.py
toolware/defaults.py
toolware/models.py
toolware/__pycache__/__init__.cpython-36.pyc
toolware/__pycache__/apps.cpython-36.pyc
toolware/__pycache__/defaults.cpython-36.pyc
toolware/__pycache__/models.cpython-36.pyc
toolware/templatetags/__init__.py
toolware/templatetags/email.py
toolware/templatetags/forms.py
toolware/templatetags/generic.py
toolware/templatetags/highlight.py
toolware/templatetags/klass.py
toolware/templatetags/rounder.py
toolware/templatetags/strings.py
toolware/templatetags/variable.py
toolware/templatetags/__pycache__/__init__.cpython-36.pyc
toolware/templatetags/__pycache__/email.cpython-36.pyc
toolware/templatetags/__pycache__/forms.cpython-36.pyc
toolware/templatetags/__pycache__/generic.cpython-36.pyc
toolware/templatetags/__pycache__/highlight.cpython-36.pyc
toolware/templatetags/__pycache__/klass.cpython-36.pyc
toolware/templatetags/__pycache__/rounder.cpython-36.pyc
toolware/templatetags/__pycache__/strings.cpython-36.pyc
toolware/templatetags/__pycache__/variable.cpython-36.pyc
toolware/tests/__init__.py
toolware/tests/settings.py
toolware/tests/tests.py
toolware/tests/urls.py
toolware/tests/__pycache__/__init__.cpython-36.pyc
toolware/tests/__pycache__/settings.cpython-36.pyc
toolware/tests/__pycache__/tests.cpython-36.pyc
toolware/tests/__pycache__/urls.cpython-36.pyc
toolware/translations/country/locale/af/LC_MESSAGES/django.po
toolware/translations/country/locale/am/LC_MESSAGES/django.po
toolware/translations/country/locale/ar/LC_MESSAGES/django.po
toolware/translations/country/locale/as/LC_MESSAGES/django.po
toolware/translations/country/locale/ast/LC_MESSAGES/django.po
toolware/translations/country/locale/az/LC_MESSAGES/django.po
toolware/translations/country/locale/be/LC_MESSAGES/django.po
toolware/translations/country/locale/bg/LC_MESSAGES/django.po
toolware/translations/country/locale/bn/LC_MESSAGES/django.po
toolware/translations/country/locale/bn_IN/LC_MESSAGES/django.po
